{
    "fldtype" : {
    	"C":{ "type": "string"},
    	"N":{ "type": "number"},
    	"D":{ "type": "string", "format": "date-time" },
    	"L":{ "type": "boolean" }
    },
    "validcode":{
        "siteid":"^[A-Z_0-9]+$"
    },
    "dataModel":{
        "instreg":"instmod",
        "instqm":"instmod",
        "instsper":"instmod",
        "instcper":"instmod",
        "insthist":"instreg",
        "instser":"instreg",
        "instcal":"instreg",
        "instresp":"instreg",
        "instread":"instreg",
        "station":"site",
        "stnini":"site",
        "bench":"site",
        "history":"site",
        "period":"site",
        "insthist":"site",
        "peaktime":"site",
        "series":"peaktime",
        "rateper":"site",
        "ratehed":"rateper",
        "ratepts":"ratehed",
        "rateeqn":"ratehed",
        "ttabhed":"rateper",
        "ttabpts":"ttabhed",
        "gaugings":"site",
        "gaugmeas":"gaugings",
        "secthed":"site",
        "sections":"secthed",
        "sectsurv":"site",
        "nrstn":"site",
        "vrwewa":"site",
        "vrwmon":"site",
        "sewsite":"site",
        "sewrconf":"site",
        "samples":"site",
        "results":"samples",
        "summary":"site",
        "wrehouse":"site",
        "grpvals":"grpkeys",
        "grplists":"grpvals",
        "logchan":"logmast",
        "macechan":"macelog",
        "macerag":"macelog",
        "minvar":"minlog",
        "codes":"codegrps",
        "mainmenu":"mngmenu",
        "usermast":"mastdoc",
        "mastdict":"mastdoc",
        "userdict":"mastdict",
        "userlog":"passwd",
        "wqvar":"variable",
        "varcon":"variable",
        "aresite":"site",
        "areasmt":"site"
    }

}